studentui/__init__.py
studentui/__main__.py
studentui/paths.py
studentui/ui_grades.py
studentui/ui_login.py
studentui/ui_selector.py
studentui/ui_timetable.py
studentui-0.4.0.dist-info/LICENSE
studentui-0.4.0.dist-info/METADATA
studentui-0.4.0.dist-info/WHEEL
studentui-0.4.0.dist-info/entry_points.txt
studentui-0.4.0.dist-info/top_level.txt
studentui-0.4.0.dist-info/RECORD
