Metadata-Version: 2.1
Name: studentui
Version: 0.4.0
Summary: A simple Qt application for fast access to Bakaláři school system.
Home-page: https://github.com/23kreny/studentui
Author: kreny
Author-email: kronerm9@gmail.com
License: UNKNOWN
Platform: UNKNOWN
Classifier: Programming Language :: Python :: 3 :: Only
Classifier: License :: OSI Approved :: GNU General Public License v3 or later (GPLv3+)
Classifier: Operating System :: OS Independent
Requires-Python: >=3.6
Requires-Dist: PySide2
Requires-Dist: bakalib (>=1.1.1)
